Jarvis_mini/DesiJarvis.py
Jarvis_mini/__init__.py
Jarvis_mini-0.0.2.dist-info/METADATA
Jarvis_mini-0.0.2.dist-info/RECORD
Jarvis_mini-0.0.2.dist-info/WHEEL
Jarvis_mini-0.0.2.dist-info/top_level.txt
