Metadata-Version: 2.1
Name: Jarvis-mini
Version: 0.0.2
Summary: Automated Hardware Scripe.
Home-page: https://github.com/mayurchhapra/education_theses
Author: Mayur Chhapra
Author-email: mayurchhapra@gmail.com
License: UNKNOWN
Platform: UNKNOWN
Classifier: Programming Language :: Python :: 3
Classifier: License :: OSI Approved :: MIT License
Classifier: Operating System :: OS Independent
